<?xml version="1.0" encoding="UTF-8"?><dictionary case_sensitive="false">
<entry count="1618">
<token>Jint.Native.Object.ObjectInstance,Delete</token>
<token>Jint.Native.Object.ObjectInstance,Delete</token>
</entry>
<entry count="1100">
<token>Jint.Native.Object.ObjectInstance,Delete</token>
<token>Jint.Native.Object.ObjectInstance,Delete</token>
<token>Jint.Native.Object.ObjectInstance,Delete</token>
</entry>
<entry count="6">
<token>Jint.Native.Object.ObjectConstructor,Construct</token>
<token>Jint.Native.Object.ObjectInstance,Put</token>
</entry>
<entry count="64">
<token>Jint.Native.Object.ObjectInstance,Delete</token>
<token>Jint.Native.Object.ObjectInstance,Delete</token>
<token>Jint.Native.Object.ObjectInstance,Delete</token>
<token>Jint.Native.Object.ObjectInstance,Delete</token>
<token>Jint.Native.Object.ObjectInstance,Delete</token>
</entry>
<entry count="582">
<token>Jint.Native.Object.ObjectInstance,Delete</token>
<token>Jint.Native.Object.ObjectInstance,Delete</token>
<token>Jint.Native.Object.ObjectInstance,Delete</token>
<token>Jint.Native.Object.ObjectInstance,Delete</token>
</entry>
</dictionary>
