<?xml version="1.0" encoding="UTF-8"?><dictionary case_sensitive="false">
<entry count="1">
<token>Microsoft.WindowsAzure.Storage.Blob.CloudBlobClient,GetContainerReference</token>
<token>Microsoft.WindowsAzure.Storage.Blob.CloudBlobContainer,CreateIfNotExists</token>
<token>Microsoft.WindowsAzure.Storage.Blob.BlobContainerPermissions,new</token>
</entry>
<entry count="1">
<token>Microsoft.WindowsAzure.Storage.Blob.CloudBlobContainer,ListBlobs</token>
<token>Microsoft.WindowsAzure.Storage.Blob.CloudBlockBlob,Delete</token>
</entry>
<entry count="1">
<token>Microsoft.WindowsAzure.Storage.Blob.BlobContainerPermissions,new</token>
<token>Microsoft.WindowsAzure.Storage.Blob.CloudBlobContainer,SetPermissions</token>
</entry>
<entry count="4">
<token>Microsoft.WindowsAzure.Storage.Blob.CloudBlockBlob,UploadFromFile</token>
<token>Microsoft.WindowsAzure.Storage.Blob.CloudBlockBlob,SetProperties</token>
</entry>
<entry count="5">
<token>Microsoft.WindowsAzure.Storage.Blob.CloudBlobContainer,GetBlockBlobReference</token>
<token>Microsoft.WindowsAzure.Storage.Blob.CloudBlockBlob,UploadFromFile</token>
</entry>
<entry count="1">
<token>Microsoft.WindowsAzure.Storage.Blob.CloudBlobContainer,CreateIfNotExists</token>
<token>Microsoft.WindowsAzure.Storage.Blob.BlobContainerPermissions,new</token>
</entry>
<entry count="1">
<token>Microsoft.WindowsAzure.Storage.Blob.CloudBlobContainer,CreateIfNotExists</token>
<token>Microsoft.WindowsAzure.Storage.Blob.BlobContainerPermissions,new</token>
<token>Microsoft.WindowsAzure.Storage.Blob.CloudBlobContainer,SetPermissions</token>
</entry>
<entry count="1">
<token>Microsoft.WindowsAzure.Storage.Blob.CloudBlobClient,GetContainerReference</token>
<token>Microsoft.WindowsAzure.Storage.Blob.CloudBlobContainer,CreateIfNotExists</token>
</entry>
<entry count="4">
<token>Microsoft.WindowsAzure.Storage.Blob.CloudBlobContainer,GetBlockBlobReference</token>
<token>Microsoft.WindowsAzure.Storage.Blob.CloudBlockBlob,UploadFromFile</token>
<token>Microsoft.WindowsAzure.Storage.Blob.CloudBlockBlob,SetProperties</token>
</entry>
<entry count="1">
<token>Microsoft.WindowsAzure.Storage.Blob.CloudBlobClient,GetContainerReference</token>
<token>Microsoft.WindowsAzure.Storage.Blob.CloudBlobContainer,CreateIfNotExists</token>
<token>Microsoft.WindowsAzure.Storage.Blob.BlobContainerPermissions,new</token>
<token>Microsoft.WindowsAzure.Storage.Blob.CloudBlobContainer,SetPermissions</token>
</entry>
</dictionary>
