<?xml version="1.0" encoding="UTF-8"?><dictionary case_sensitive="false">
<entry count="4">
<token>Microsoft.Scripting.Hosting.ScriptEngine,CreateScope</token>
<token>Microsoft.Scripting.Hosting.CompiledCode,Execute</token>
</entry>
<entry count="128">
<token>Microsoft.Scripting.Hosting.ScriptRuntime,LoadAssembly</token>
<token>Microsoft.Scripting.Hosting.ScriptRuntime,LoadAssembly</token>
<token>Microsoft.Scripting.Hosting.ScriptEngine,SetSearchPaths</token>
</entry>
<entry count="8">
<token>Microsoft.Scripting.Hosting.ScriptEngine,CreateScriptSourceFromString</token>
<token>Microsoft.Scripting.Hosting.ScriptSource,Execute</token>
</entry>
<entry count="8">
<token>Microsoft.Scripting.Hosting.ScriptEngine,CreateScriptSourceFromString</token>
<token>Microsoft.Scripting.Hosting.ScriptSource,Compile</token>
</entry>
<entry count="128">
<token>Microsoft.Scripting.Hosting.ScriptRuntime,LoadAssembly</token>
<token>Microsoft.Scripting.Hosting.ScriptRuntime,LoadAssembly</token>
</entry>
<entry count="4">
<token>Microsoft.Scripting.Hosting.ScriptSource,Compile</token>
<token>Microsoft.Scripting.Hosting.ScriptEngine,CreateScope</token>
<token>Microsoft.Scripting.Hosting.CompiledCode,Execute</token>
</entry>
<entry count="128">
<token>Microsoft.Scripting.Hosting.ScriptRuntime,LoadAssembly</token>
<token>Microsoft.Scripting.Hosting.ScriptEngine,SetSearchPaths</token>
</entry>
<entry count="4">
<token>Microsoft.Scripting.Hosting.ScriptSource,Compile</token>
<token>Microsoft.Scripting.Hosting.ScriptEngine,CreateScope</token>
</entry>
<entry count="4">
<token>Microsoft.Scripting.Hosting.ScriptEngine,CreateScriptSourceFromString</token>
<token>Microsoft.Scripting.Hosting.ScriptSource,Compile</token>
<token>Microsoft.Scripting.Hosting.ScriptEngine,CreateScope</token>
</entry>
<entry count="4">
<token>Microsoft.Scripting.Hosting.ScriptEngine,CreateScriptSourceFromString</token>
<token>Microsoft.Scripting.Hosting.ScriptSource,Compile</token>
<token>Microsoft.Scripting.Hosting.ScriptEngine,CreateScope</token>
<token>Microsoft.Scripting.Hosting.CompiledCode,Execute</token>
</entry>
</dictionary>
