<?xml version="1.0" encoding="UTF-8"?><dictionary case_sensitive="false">
<entry count="20">
<token>Microsoft.CodeAnalysis.CodeFixes.CodeFixContext,new</token>
<token>Microsoft.CodeAnalysis.CodeFixes.CodeFixProvider,RegisterCodeFixesAsync</token>
</entry>
<entry count="64">
<token>Microsoft.CodeAnalysis.CodeFixes.CodeFixProvider,GetFixAllProvider</token>
<token>Microsoft.CodeAnalysis.CodeFixes.FixAllProvider,GetSupportedFixAllScopes</token>
<token>Microsoft.CodeAnalysis.CodeFixes.FixAllContext,new</token>
</entry>
<entry count="12473">
<token>Microsoft.CodeAnalysis.CodeFixes.CodeFixContext,RegisterCodeFix</token>
<token>Microsoft.CodeAnalysis.CodeFixes.CodeFixContext,RegisterCodeFix</token>
</entry>
<entry count="64">
<token>Microsoft.CodeAnalysis.CodeFixes.FixAllProvider,GetSupportedFixAllScopes</token>
<token>Microsoft.CodeAnalysis.CodeFixes.FixAllContext,new</token>
</entry>
<entry count="64">
<token>Microsoft.CodeAnalysis.CodeFixes.CodeFixProvider,GetFixAllProvider</token>
<token>Microsoft.CodeAnalysis.CodeFixes.FixAllProvider,GetSupportedFixAllScopes</token>
</entry>
<entry count="864">
<token>Microsoft.CodeAnalysis.CodeFixes.CodeFixContext,RegisterCodeFix</token>
<token>Microsoft.CodeAnalysis.CodeFixes.CodeFixContext,RegisterCodeFix</token>
<token>Microsoft.CodeAnalysis.CodeFixes.CodeFixContext,RegisterCodeFix</token>
</entry>
</dictionary>
