<?xml version="1.0" encoding="UTF-8"?><dictionary case_sensitive="false">
<entry count="3">
<token>Mono.Debugging.Client.Backtrace,new</token>
<token>Mono.Debugging.Client.DebuggerSession,OnTargetEvent</token>
</entry>
<entry count="1">
<token>Mono.Debugging.Client.SourceLocation,new</token>
<token>Mono.Debugging.Client.StackFrame,new</token>
</entry>
<entry count="1">
<token>Mono.Debugging.Client.BreakpointStore,Clear</token>
<token>Mono.Debugging.Client.DebuggerSession,Dispose</token>
</entry>
<entry count="3">
<token>Mono.Debugging.Client.TargetEventArgs,new</token>
<token>Mono.Debugging.Client.Backtrace,new</token>
<token>Mono.Debugging.Client.DebuggerSession,OnTargetEvent</token>
</entry>
<entry count="3">
<token>Mono.Debugging.Client.TargetEventArgs,new</token>
<token>Mono.Debugging.Client.Backtrace,new</token>
</entry>
<entry count="2">
<token>Mono.Debugging.Client.BreakEventInfo,new</token>
<token>Mono.Debugging.Client.BreakEventInfo,SetStatus</token>
</entry>
<entry count="1">
<token>Mono.Debugging.Client.TargetEventArgs,new</token>
<token>Mono.Debugging.Client.DebuggerSession,OnTargetEvent</token>
</entry>
</dictionary>
