<?xml version="1.0" encoding="UTF-8"?><dictionary case_sensitive="false">
<entry count="1">
<token>Phidgets.Accelerometer,new</token>
<token>Phidgets.Phidget,open</token>
</entry>
<entry count="1">
<token>Phidgets.Encoder,new</token>
<token>Phidgets.Phidget,open</token>
</entry>
<entry count="2">
<token>Phidgets.Manager,new</token>
<token>Phidgets.Manager,open</token>
</entry>
<entry count="1">
<token>Phidgets.InterfaceKit,new</token>
<token>Phidgets.Phidget,open</token>
</entry>
<entry count="1">
<token>Phidgets.RFID,new</token>
<token>Phidgets.Phidget,open</token>
</entry>
</dictionary>
