<?xml version="1.0" encoding="UTF-8"?><dictionary case_sensitive="false">
<entry count="3">
<token>SchwabenCode.QuickIO.QuickIOFile,Exists</token>
<token>SchwabenCode.QuickIO.QuickIOFile,Exists</token>
<token>SchwabenCode.QuickIO.QuickIOFile,Delete</token>
</entry>
<entry count="21">
<token>SchwabenCode.QuickIO.QuickIOFile,Exists</token>
<token>SchwabenCode.QuickIO.QuickIOFile,SetAttributes</token>
<token>SchwabenCode.QuickIO.QuickIOFile,Delete</token>
</entry>
<entry count="24">
<token>SchwabenCode.QuickIO.QuickIODirectory,Exists</token>
<token>SchwabenCode.QuickIO.QuickIODirectory,EnumerateDirectoryPaths</token>
<token>SchwabenCode.QuickIO.QuickIODirectoryInfo,new</token>
<token>SchwabenCode.QuickIO.QuickIODirectory,EnumerateFilePaths</token>
<token>SchwabenCode.QuickIO.QuickIODirectory,Delete</token>
</entry>
<entry count="9">
<token>SchwabenCode.QuickIO.QuickIODirectory,Create</token>
<token>SchwabenCode.QuickIO.QuickIOFile,Exists</token>
<token>SchwabenCode.QuickIO.QuickIOFile,SetAttributes</token>
</entry>
<entry count="9">
<token>SchwabenCode.QuickIO.QuickIODirectory,Exists</token>
<token>SchwabenCode.QuickIO.QuickIODirectory,Create</token>
<token>SchwabenCode.QuickIO.QuickIOFile,Exists</token>
<token>SchwabenCode.QuickIO.QuickIOFile,SetAttributes</token>
</entry>
<entry count="18">
<token>SchwabenCode.QuickIO.QuickIOFile,Delete</token>
<token>SchwabenCode.QuickIO.QuickIOFile,Create</token>
</entry>
<entry count="18">
<token>SchwabenCode.QuickIO.QuickIOFile,SetAttributes</token>
<token>SchwabenCode.QuickIO.QuickIOFile,Delete</token>
<token>SchwabenCode.QuickIO.QuickIOFile,Create</token>
<token>SchwabenCode.QuickIO.QuickIOFile,Open</token>
</entry>
<entry count="24">
<token>SchwabenCode.QuickIO.QuickIODirectoryInfo,new</token>
<token>SchwabenCode.QuickIO.QuickIODirectory,EnumerateFilePaths</token>
<token>SchwabenCode.QuickIO.QuickIODirectory,Delete</token>
</entry>
<entry count="12">
<token>SchwabenCode.QuickIO.QuickIODirectory,EnumerateDirectoryPaths</token>
<token>SchwabenCode.QuickIO.QuickIODirectoryInfo,new</token>
<token>SchwabenCode.QuickIO.QuickIODirectoryInfo,new</token>
<token>SchwabenCode.QuickIO.QuickIODirectory,EnumerateFilePaths</token>
</entry>
<entry count="18">
<token>SchwabenCode.QuickIO.QuickIODirectory,Exists</token>
<token>SchwabenCode.QuickIO.QuickIOFile,Exists</token>
</entry>
<entry count="42">
<token>SchwabenCode.QuickIO.QuickIODirectoryInfo,new</token>
<token>SchwabenCode.QuickIO.QuickIODirectory,EnumerateFilePaths</token>
</entry>
<entry count="18">
<token>SchwabenCode.QuickIO.QuickIOFile,Delete</token>
<token>SchwabenCode.QuickIO.QuickIOFile,Create</token>
<token>SchwabenCode.QuickIO.QuickIOFile,Open</token>
</entry>
<entry count="9">
<token>SchwabenCode.QuickIO.QuickIODirectory,Exists</token>
<token>SchwabenCode.QuickIO.QuickIODirectory,Create</token>
<token>SchwabenCode.QuickIO.QuickIOFile,Exists</token>
<token>SchwabenCode.QuickIO.QuickIOFile,Create</token>
</entry>
<entry count="9">
<token>SchwabenCode.QuickIO.QuickIODirectory,Create</token>
<token>SchwabenCode.QuickIO.QuickIOFile,Exists</token>
<token>SchwabenCode.QuickIO.QuickIOFile,Create</token>
<token>SchwabenCode.QuickIO.QuickIOFile,Open</token>
</entry>
<entry count="21">
<token>SchwabenCode.QuickIO.QuickIOFile,SetAttributes</token>
<token>SchwabenCode.QuickIO.QuickIOFile,Delete</token>
</entry>
<entry count="9">
<token>SchwabenCode.QuickIO.QuickIODirectory,Exists</token>
<token>SchwabenCode.QuickIO.QuickIOFile,Exists</token>
<token>SchwabenCode.QuickIO.QuickIOFile,SetAttributes</token>
</entry>
<entry count="9">
<token>SchwabenCode.QuickIO.QuickIODirectory,Exists</token>
<token>SchwabenCode.QuickIO.QuickIOFile,Exists</token>
<token>SchwabenCode.QuickIO.QuickIOFile,Create</token>
<token>SchwabenCode.QuickIO.QuickIOFile,Open</token>
</entry>
<entry count="12">
<token>SchwabenCode.QuickIO.QuickIODirectory,Exists</token>
<token>SchwabenCode.QuickIO.QuickIODirectory,EnumerateDirectoryPaths</token>
<token>SchwabenCode.QuickIO.QuickIODirectoryInfo,new</token>
<token>SchwabenCode.QuickIO.QuickIODirectoryInfo,new</token>
</entry>
<entry count="9">
<token>SchwabenCode.QuickIO.QuickIODirectory,Exists</token>
<token>SchwabenCode.QuickIO.QuickIOFile,Exists</token>
<token>SchwabenCode.QuickIO.QuickIOFile,SetAttributes</token>
<token>SchwabenCode.QuickIO.QuickIOFile,Delete</token>
<token>SchwabenCode.QuickIO.QuickIOFile,Create</token>
</entry>
<entry count="9">
<token>SchwabenCode.QuickIO.QuickIODirectory,Create</token>
<token>SchwabenCode.QuickIO.QuickIOFile,Exists</token>
<token>SchwabenCode.QuickIO.QuickIOFile,SetAttributes</token>
<token>SchwabenCode.QuickIO.QuickIOFile,Delete</token>
</entry>
<entry count="12">
<token>SchwabenCode.QuickIO.QuickIOFile,Exists</token>
<token>SchwabenCode.QuickIO.QuickIOFile,Exists</token>
</entry>
<entry count="9">
<token>SchwabenCode.QuickIO.QuickIODirectory,Create</token>
<token>SchwabenCode.QuickIO.QuickIOFile,Exists</token>
<token>SchwabenCode.QuickIO.QuickIOFile,SetAttributes</token>
<token>SchwabenCode.QuickIO.QuickIOFile,Delete</token>
<token>SchwabenCode.QuickIO.QuickIOFile,Create</token>
</entry>
<entry count="21">
<token>SchwabenCode.QuickIO.QuickIODirectory,Exists</token>
<token>SchwabenCode.QuickIO.QuickIODirectory,Create</token>
</entry>
<entry count="12">
<token>SchwabenCode.QuickIO.QuickIODirectoryInfo,new</token>
<token>SchwabenCode.QuickIO.QuickIODirectoryInfo,new</token>
</entry>
<entry count="30">
<token>SchwabenCode.QuickIO.QuickIODirectory,EnumerateDirectoryPaths</token>
<token>SchwabenCode.QuickIO.QuickIODirectoryInfo,new</token>
<token>SchwabenCode.QuickIO.QuickIODirectory,EnumerateFilePaths</token>
</entry>
<entry count="18">
<token>SchwabenCode.QuickIO.QuickIOFile,SetAttributes</token>
<token>SchwabenCode.QuickIO.QuickIOFile,Delete</token>
<token>SchwabenCode.QuickIO.QuickIOFile,Create</token>
</entry>
<entry count="3">
<token>SchwabenCode.QuickIO.QuickIOFile,Exists</token>
<token>SchwabenCode.QuickIO.QuickIOFile,Delete</token>
</entry>
<entry count="18">
<token>SchwabenCode.QuickIO.QuickIODirectory,Create</token>
<token>SchwabenCode.QuickIO.QuickIOFile,Exists</token>
</entry>
<entry count="12">
<token>SchwabenCode.QuickIO.QuickIODirectoryInfo,new</token>
<token>SchwabenCode.QuickIO.QuickIODirectoryInfo,new</token>
<token>SchwabenCode.QuickIO.QuickIODirectory,EnumerateFilePaths</token>
</entry>
<entry count="9">
<token>SchwabenCode.QuickIO.QuickIODirectory,Exists</token>
<token>SchwabenCode.QuickIO.QuickIOFile,Exists</token>
<token>SchwabenCode.QuickIO.QuickIOFile,Create</token>
</entry>
<entry count="18">
<token>SchwabenCode.QuickIO.QuickIOFile,Exists</token>
<token>SchwabenCode.QuickIO.QuickIOFile,SetAttributes</token>
<token>SchwabenCode.QuickIO.QuickIOFile,Delete</token>
<token>SchwabenCode.QuickIO.QuickIOFile,Create</token>
<token>SchwabenCode.QuickIO.QuickIOFile,Open</token>
</entry>
<entry count="18">
<token>SchwabenCode.QuickIO.QuickIODirectory,Exists</token>
<token>SchwabenCode.QuickIO.QuickIODirectory,Create</token>
<token>SchwabenCode.QuickIO.QuickIOFile,Exists</token>
</entry>
<entry count="18">
<token>SchwabenCode.QuickIO.QuickIOFile,Exists</token>
<token>SchwabenCode.QuickIO.QuickIOFile,Create</token>
</entry>
<entry count="12">
<token>SchwabenCode.QuickIO.QuickIODirectory,Exists</token>
<token>SchwabenCode.QuickIO.QuickIODirectory,EnumerateDirectoryPaths</token>
<token>SchwabenCode.QuickIO.QuickIODirectoryInfo,new</token>
<token>SchwabenCode.QuickIO.QuickIODirectoryInfo,new</token>
<token>SchwabenCode.QuickIO.QuickIODirectory,EnumerateFilePaths</token>
</entry>
<entry count="24">
<token>SchwabenCode.QuickIO.QuickIODirectory,EnumerateDirectoryPaths</token>
<token>SchwabenCode.QuickIO.QuickIODirectoryInfo,new</token>
<token>SchwabenCode.QuickIO.QuickIODirectory,EnumerateFilePaths</token>
<token>SchwabenCode.QuickIO.QuickIODirectory,Delete</token>
</entry>
<entry count="18">
<token>SchwabenCode.QuickIO.QuickIOFile,Exists</token>
<token>SchwabenCode.QuickIO.QuickIOFile,Create</token>
<token>SchwabenCode.QuickIO.QuickIOFile,Open</token>
</entry>
<entry count="24">
<token>SchwabenCode.QuickIO.QuickIODirectory,EnumerateFilePaths</token>
<token>SchwabenCode.QuickIO.QuickIODirectory,Delete</token>
</entry>
<entry count="30">
<token>SchwabenCode.QuickIO.QuickIOFile,Exists</token>
<token>SchwabenCode.QuickIO.QuickIOFile,SetAttributes</token>
</entry>
<entry count="9">
<token>SchwabenCode.QuickIO.QuickIODirectory,Exists</token>
<token>SchwabenCode.QuickIO.QuickIODirectory,Create</token>
<token>SchwabenCode.QuickIO.QuickIOFile,Exists</token>
<token>SchwabenCode.QuickIO.QuickIOFile,SetAttributes</token>
<token>SchwabenCode.QuickIO.QuickIOFile,Delete</token>
</entry>
<entry count="9">
<token>SchwabenCode.QuickIO.QuickIODirectory,Create</token>
<token>SchwabenCode.QuickIO.QuickIOFile,Exists</token>
<token>SchwabenCode.QuickIO.QuickIOFile,Create</token>
</entry>
<entry count="30">
<token>SchwabenCode.QuickIO.QuickIODirectory,Exists</token>
<token>SchwabenCode.QuickIO.QuickIODirectory,EnumerateDirectoryPaths</token>
<token>SchwabenCode.QuickIO.QuickIODirectoryInfo,new</token>
<token>SchwabenCode.QuickIO.QuickIODirectory,EnumerateFilePaths</token>
</entry>
<entry count="42">
<token>SchwabenCode.QuickIO.QuickIODirectory,Exists</token>
<token>SchwabenCode.QuickIO.QuickIODirectory,EnumerateDirectoryPaths</token>
<token>SchwabenCode.QuickIO.QuickIODirectoryInfo,new</token>
</entry>
<entry count="9">
<token>SchwabenCode.QuickIO.QuickIODirectory,Exists</token>
<token>SchwabenCode.QuickIO.QuickIODirectory,Create</token>
<token>SchwabenCode.QuickIO.QuickIOFile,Exists</token>
<token>SchwabenCode.QuickIO.QuickIOFile,Create</token>
<token>SchwabenCode.QuickIO.QuickIOFile,Open</token>
</entry>
<entry count="36">
<token>SchwabenCode.QuickIO.QuickIOFile,Create</token>
<token>SchwabenCode.QuickIO.QuickIOFile,Open</token>
</entry>
<entry count="3">
<token>SchwabenCode.QuickIO.QuickIOFile,Exists</token>
<token>SchwabenCode.QuickIO.QuickIOFile,SetAttributes</token>
<token>SchwabenCode.QuickIO.QuickIOFile,Copy</token>
</entry>
<entry count="42">
<token>SchwabenCode.QuickIO.QuickIODirectory,Exists</token>
<token>SchwabenCode.QuickIO.QuickIODirectory,EnumerateDirectoryPaths</token>
</entry>
<entry count="3">
<token>SchwabenCode.QuickIO.QuickIOFile,SetAttributes</token>
<token>SchwabenCode.QuickIO.QuickIOFile,Copy</token>
</entry>
<entry count="9">
<token>SchwabenCode.QuickIO.QuickIODirectory,Exists</token>
<token>SchwabenCode.QuickIO.QuickIOFile,Exists</token>
<token>SchwabenCode.QuickIO.QuickIOFile,SetAttributes</token>
<token>SchwabenCode.QuickIO.QuickIOFile,Delete</token>
</entry>
<entry count="18">
<token>SchwabenCode.QuickIO.QuickIOFile,Exists</token>
<token>SchwabenCode.QuickIO.QuickIOFile,SetAttributes</token>
<token>SchwabenCode.QuickIO.QuickIOFile,Delete</token>
<token>SchwabenCode.QuickIO.QuickIOFile,Create</token>
</entry>
<entry count="3">
<token>SchwabenCode.QuickIO.QuickIOFile,Exists</token>
<token>SchwabenCode.QuickIO.QuickIOFile,Copy</token>
</entry>
<entry count="42">
<token>SchwabenCode.QuickIO.QuickIODirectory,EnumerateDirectoryPaths</token>
<token>SchwabenCode.QuickIO.QuickIODirectoryInfo,new</token>
</entry>
<entry count="12">
<token>SchwabenCode.QuickIO.QuickIODirectory,EnumerateDirectoryPaths</token>
<token>SchwabenCode.QuickIO.QuickIODirectoryInfo,new</token>
<token>SchwabenCode.QuickIO.QuickIODirectoryInfo,new</token>
</entry>
</dictionary>
