<?xml version="1.0" encoding="UTF-8"?><dictionary case_sensitive="false">
<entry count="12">
<token>System.Data.Linq.Mapping.MetaModel,GetTable</token>
<token>System.Data.Linq.Mapping.MetaType,GetDataMember</token>
</entry>
<entry count="2">
<token>System.Data.Linq.Mapping.AttributeMappingSource,new</token>
<token>System.Data.Linq.Mapping.MappingSource,GetModel</token>
<token>System.Data.Linq.Mapping.MetaModel,GetTables</token>
</entry>
<entry count="36">
<token>System.Data.Linq.Mapping.MetaModel,GetTable</token>
<token>System.Data.Linq.Mapping.MetaModel,GetTable</token>
</entry>
<entry count="2">
<token>System.Data.Linq.Mapping.AttributeMappingSource,new</token>
<token>System.Data.Linq.Mapping.MappingSource,GetModel</token>
</entry>
<entry count="4">
<token>System.Data.Linq.Mapping.MappingSource,GetModel</token>
<token>System.Data.Linq.Mapping.MetaModel,GetTables</token>
</entry>
</dictionary>
